snacktime/__init__.py
snacktime/__main__.py
snacktime/core.py
snacktime-0.5.1.dist-info/licenses/LICENSE
snacktime-0.5.1.dist-info/METADATA
snacktime-0.5.1.dist-info/WHEEL
snacktime-0.5.1.dist-info/entry_points.txt
snacktime-0.5.1.dist-info/top_level.txt
snacktime-0.5.1.dist-info/RECORD
