Metadata-Version: 2.4
Name: snacktime
Version: 0.5.1
Summary: CLI that gives a random snack, a simple salad recipe, a random vegetable, or a sweet treat.
Author-email: Ezra Shapiro <ems9856@nyu.edu>, Athena Luo <athenaluoxy@gmail.com>, Jasir Nawar <jn2691@nyu.edu>, Hanqi Gui <hg2542@nyu.edu>, Kaiyuan Wu <wkyklmf@gmail.com>
Maintainer-email: Ezra Shapiro <ems9856@nyu.edu>, Athena Luo <athenaluoxy@gmail.com>, Jasir Nawar <jn2691@nyu.edu>, Hanqi Gui <hg2542@nyu.edu>, Kaiyuan Wu <wkyklmf@gmail.com>
License:                     GNU GENERAL PUBLIC LICENSE
Project-URL: Homepage, https://github.com/swe-students-fall2025/3-python-package-team_solace
Project-URL: Repository, https://github.com/swe-students-fall2025/3-python-package-team_solace.git
Project-URL: Bug Tracker, https://github.com/swe-students-fall2025/3-python-package-team_solace/issues
Requires-Python: >=3.9
License-File: LICENSE
Provides-Extra: dev
Requires-Dist: pytest; extra == "dev"
Dynamic: license-file
